hyperdiv_session/__init__.py
hyperdiv_session/assets/session.js
hyperdiv_session/crypto.py
hyperdiv_session/tests/__init__.py
hyperdiv_session/tests/test_crypto.py
hyperdiv_session/tests/test_session.py
hyperdiv_session-0.1.1.dist-info/LICENSE
hyperdiv_session-0.1.1.dist-info/METADATA
hyperdiv_session-0.1.1.dist-info/WHEEL
hyperdiv_session-0.1.1.dist-info/RECORD
