Metadata-Version: 2.1
Name: hyperdiv-session
Version: 0.1.1
Summary: Session management for hyperdiv
License: Apache-2.0
Keywords: hyperdiv,reactive,ui,web,framework,hyperdiv-session
Author: Vladimir Ignatev
Author-email: ya.na.pochte@gmail.com
Requires-Python: >=3.9,<4.0
Classifier: Environment :: Web Environment
Classifier: Intended Audience :: Developers
Classifier: License :: OSI Approved :: Apache Software License
Classifier: Programming Language :: Python
Classifier: Programming Language :: Python :: 3
Classifier: Programming Language :: Python :: 3.9
Classifier: Programming Language :: Python :: 3.10
Classifier: Programming Language :: Python :: 3.11
Classifier: Programming Language :: Python :: 3.12
Classifier: Topic :: Internet :: WWW/HTTP :: Dynamic Content
Classifier: Topic :: Software Development :: Libraries :: Application Frameworks
Requires-Dist: hyperdiv (>=0.1.8,<0.2.0)
